dc_logging/__init__.py
dc_logging/main.py
dc_logging-0.0.2.dist-info/LICENSE
dc_logging-0.0.2.dist-info/METADATA
dc_logging-0.0.2.dist-info/WHEEL
dc_logging-0.0.2.dist-info/top_level.txt
dc_logging-0.0.2.dist-info/RECORD
