Metadata-Version: 2.1
Name: dc-logging
Version: 0.0.2
Summary: Easy logging setup for small projects.
Author-email: Daniel Caballero <danielcaballero88@gmail.com>
License: MIT License
Project-URL: Homepage, https://github.com/danielcaballero88/dc-logging
Keywords: logging
Classifier: License :: OSI Approved :: MIT License
Classifier: Programming Language :: Python
Classifier: Programming Language :: Python :: 3
Requires-Python: >=3.6
License-File: LICENSE
Provides-Extra: dev
Requires-Dist: black ; extra == 'dev'
Requires-Dist: isort ; extra == 'dev'
Requires-Dist: pylint ; extra == 'dev'
Requires-Dist: mypy ; extra == 'dev'
